CHANGES.rst
CONTRIBUTORS.rst
DEVELOP.rst
LICENSE.GPL
LICENSE.rst
MANIFEST.in
README.rst
requirements.txt
setup.cfg
setup.py
tox.ini
docs/conf.py
docs/index.rst
src/cs/__init__.py
src/cs.zestreleaser.eggbuilder.egg-info/PKG-INFO
src/cs.zestreleaser.eggbuilder.egg-info/SOURCES.txt
src/cs.zestreleaser.eggbuilder.egg-info/dependency_links.txt
src/cs.zestreleaser.eggbuilder.egg-info/entry_points.txt
src/cs.zestreleaser.eggbuilder.egg-info/namespace_packages.txt
src/cs.zestreleaser.eggbuilder.egg-info/not-zip-safe
src/cs.zestreleaser.eggbuilder.egg-info/requires.txt
src/cs.zestreleaser.eggbuilder.egg-info/top_level.txt
src/cs/zestreleaser/__init__.py
src/cs/zestreleaser/eggbuilder/__init__.py
src/cs/zestreleaser/eggbuilder/builder.py