Metadata-Version: 2.1
Name: cs.zestreleaser.eggbuilder
Version: 1.0.1
Summary: An add-on for Plone
Home-page: https://github.com/collective/cs.zestreleaser.eggbuilder
Author: Mikel Larreategi
Author-email: mlarreategi@codesyntax.com
License: GPL version 2
Project-URL: PyPI, https://pypi.python.org/pypi/cs.zestreleaser.eggbuilder
Project-URL: Source, https://github.com/collective/cs.zestreleaser.eggbuilder
Project-URL: Tracker, https://github.com/collective/cs.zestreleaser.eggbuilder/issues
Keywords: Python Plone CMS
Platform: UNKNOWN
Classifier: Programming Language :: Python
Classifier: Programming Language :: Python :: 2.7
Classifier: Programming Language :: Python :: 3.7
Classifier: Operating System :: OS Independent
Classifier: License :: OSI Approved :: GNU General Public License v2 (GPLv2)
Provides-Extra: test
